gwtt/__init__.py
gwtt/script.py
galaxy_workflow_tool_tests-0.0.2.dist-info/LICENSE
galaxy_workflow_tool_tests-0.0.2.dist-info/METADATA
galaxy_workflow_tool_tests-0.0.2.dist-info/WHEEL
galaxy_workflow_tool_tests-0.0.2.dist-info/entry_points.txt
galaxy_workflow_tool_tests-0.0.2.dist-info/top_level.txt
galaxy_workflow_tool_tests-0.0.2.dist-info/RECORD
